DFS_Wrapper/CustomExceptions.py
DFS_Wrapper/DFS_Base.py
DFS_Wrapper/PrizePicks.py
DFS_Wrapper/Underdog.py
DFS_Wrapper/__init__.py
DFS_Wrapper/default_mapper.py
api_dfs_wrapper-1.1.10.dist-info/METADATA
api_dfs_wrapper-1.1.10.dist-info/WHEEL
api_dfs_wrapper-1.1.10.dist-info/top_level.txt
api_dfs_wrapper-1.1.10.dist-info/RECORD
