Metadata-Version: 2.1
Name: api-dfs-wrapper
Version: 1.1.10
Summary: DFS Wrapper to easily access DFS Books API
Requires-Dist: certifi ==2024.12.14
Requires-Dist: charset-normalizer ==3.4.1
Requires-Dist: idna ==3.10
Requires-Dist: requests ==2.32.3
Requires-Dist: urllib3 ==2.3.0
Requires-Dist: pytz ==2024.2
